pip4a/__init__.py
pip4a/__main__.py
pip4a/_version.py
pip4a/_version.pyi
pip4a/arg_parser.py
pip4a/cli.py
pip4a/collection.py
pip4a/config.py
pip4a/output.py
pip4a/tree.py
pip4a/utils.py
pip4a/subcommands/__init__.py
pip4a/subcommands/checker.py
pip4a/subcommands/inspector.py
pip4a/subcommands/installer.py
pip4a/subcommands/lister.py
pip4a/subcommands/treemaker.py
pip4a/subcommands/uninstaller.py
pip4a-0.2.17.dist-info/LICENSE
pip4a-0.2.17.dist-info/METADATA
pip4a-0.2.17.dist-info/WHEEL
pip4a-0.2.17.dist-info/entry_points.txt
pip4a-0.2.17.dist-info/top_level.txt
pip4a-0.2.17.dist-info/RECORD
